html2term/__init__.py
html2term/core.py
html2term-1.0.0.dist-info/licenses/LICENSE
html2term-1.0.0.dist-info/METADATA
html2term-1.0.0.dist-info/WHEEL
html2term-1.0.0.dist-info/top_level.txt
html2term-1.0.0.dist-info/RECORD
