Metadata-Version: 2.4
Name: html2term
Version: 1.0.0
Summary: Parse minimal HTML-like markup into ANSI-styled terminal output
Author-email: Nikita Berger <bergernikita1807@gmail.com>
License: Apache License (2.0)
Project-URL: Homepage, https://github.com/Nikityyy/html2term
Project-URL: Bug Tracker, https://github.com/Nikityyy/html2term/issues
Keywords: html,terminal,ansi,color,style,cli
Classifier: Programming Language :: Python :: 3
Classifier: Programming Language :: Python :: 3.7
Classifier: Programming Language :: Python :: 3.8
Classifier: Programming Language :: Python :: 3.9
Classifier: Programming Language :: Python :: 3.10
Classifier: Programming Language :: Python :: 3.11
Classifier: Programming Language :: Python :: 3.12
Classifier: License :: OSI Approved :: Apache Software License
Classifier: Operating System :: OS Independent
Classifier: Environment :: Console
Classifier: Topic :: Terminals
Classifier: Topic :: Utilities
Requires-Python: >=3.7
License-File: LICENSE
Dynamic: license-file
